sarvam_conv_ai_sd_transcript_sample-1.0.13.1.dev0.dist-info/licenses/LICENSE
sarvam_conv_ai_sdk/__init__.py
sarvam_conv_ai_sdk/audio_interface.py
sarvam_conv_ai_sdk/conversation.py
sarvam_conv_ai_sdk/default_audio_interface.py
sarvam_conv_ai_sdk/py.typed
sarvam_conv_ai_sdk/tool.py
sarvam_conv_ai_sdk/examples/async_audio_example.py
sarvam_conv_ai_sdk/examples/async_text_example.py
sarvam_conv_ai_sdk/messages/__init__.py
sarvam_conv_ai_sdk/messages/actions.py
sarvam_conv_ai_sdk/messages/audio.py
sarvam_conv_ai_sdk/messages/base.py
sarvam_conv_ai_sdk/messages/config.py
sarvam_conv_ai_sdk/messages/events.py
sarvam_conv_ai_sdk/messages/system.py
sarvam_conv_ai_sdk/messages/text.py
sarvam_conv_ai_sdk/messages/types.py
tests/conftest.py
tests/test_context_functions.py
tests/test_text_conversation.py
tests/test_tool_output.py
tests/test_tools.py
sarvam_conv_ai_sd_transcript_sample-1.0.13.1.dev0.dist-info/METADATA
sarvam_conv_ai_sd_transcript_sample-1.0.13.1.dev0.dist-info/WHEEL
sarvam_conv_ai_sd_transcript_sample-1.0.13.1.dev0.dist-info/top_level.txt
sarvam_conv_ai_sd_transcript_sample-1.0.13.1.dev0.dist-info/RECORD
