Metadata-Version: 2.4
Name: sarvam-conv-ai-sd-transcript-sample
Version: 1.0.13.1.dev0
Summary: The Sarvam Conversational AI SDK is a Python package that helps developers build and extend conversational agents.
Requires-Python: >=3.11
License-File: LICENSE
Requires-Dist: fastapi>=0.118.2
Requires-Dist: httpx>=0.28.1
Requires-Dist: pydantic>=2.11.7
Requires-Dist: uvicorn>=0.37.0
Requires-Dist: websockets>=15.0.1
Provides-Extra: all
Requires-Dist: pyaudio>=0.2.14; extra == "all"
Dynamic: license-file
